{
    "version": "0.1.14",
    "architecture": {
        "64bit": {
            "url": "https://github.com/godaddy/ans-sdk-go/releases/download/v0.1.14/ans-cli_0.1.14_windows_amd64.zip",
            "bin": [
                "ans-cli.exe"
            ],
            "hash": "ef66ca397af232e7f75691e44ee12c92a349b73f13616affadfadd9a0df24bf1"
        },
        "arm64": {
            "url": "https://github.com/godaddy/ans-sdk-go/releases/download/v0.1.14/ans-cli_0.1.14_windows_arm64.zip",
            "bin": [
                "ans-cli.exe"
            ],
            "hash": "f850ff69c760a7fecac0d0a55fcf783ebc8893a940aeee9e4eb5925e0ad67f86"
        }
    },
    "homepage": "https://github.com/godaddy/ans-sdk-go",
    "license": "MIT",
    "description": "Command-line tool for the Agent Name Service (ANS) Registry"
}
